defectmat/__init__.py
defectmat-2024.3.24.dist-info/LICENSE
defectmat-2024.3.24.dist-info/METADATA
defectmat-2024.3.24.dist-info/WHEEL
defectmat-2024.3.24.dist-info/top_level.txt
defectmat-2024.3.24.dist-info/RECORD
